voxcharta_my_voting_record/__init__.py
voxcharta_my_voting_record/extract.py
voxcharta_my_voting_record/logger.py
voxcharta_my_voting_record-0.4.1.data/scripts/vox_run
voxcharta_my_voting_record-0.4.1.dist-info/LICENSE
voxcharta_my_voting_record-0.4.1.dist-info/METADATA
voxcharta_my_voting_record-0.4.1.dist-info/WHEEL
voxcharta_my_voting_record-0.4.1.dist-info/top_level.txt
voxcharta_my_voting_record-0.4.1.dist-info/RECORD
