Metadata-Version: 2.1
Name: voxcharta-my-voting-record
Version: 0.4.1
Summary: A Python tool to extract information from VoxCharta My Voting Records HTML
Home-page: https://github.com/astrochun/voxcharta-my-voting-record
Author: Chun Ly
Author-email: astro.chun@gmail.com
Maintainer: Chun Ly
Maintainer-email: astro.chun@gmail.com
License: GNU GPLv3
Project-URL: Tracker, https://github.com/astrochun/voxcharta-my-voting-record/issues
Project-URL: Source, https://github.com/astrochun/voxcharta-my-voting-record
Project-URL: Documentation, https://github.com/astrochun/voxcharta-my-voting-record/blob/main/README.md
Platform: UNKNOWN
Classifier: Development Status :: 4 - Beta
Classifier: Programming Language :: Python :: 3 :: Only
Classifier: Programming Language :: Python :: 3.7
Classifier: Programming Language :: Python :: 3.8
Classifier: Programming Language :: Python :: 3.9
Classifier: Programming Language :: Python :: 3.10
Requires-Python: <3.11,>=3.7
License-File: LICENSE
Requires-Dist: pandas (>=1.1.5)
Requires-Dist: beautifulsoup4 (>=4.9.3)
Requires-Dist: Typer (<1.0.0,>=0.4.0)
Requires-Dist: Click (==8.0.4)
Requires-Dist: rich (<13.0.0,>=12.2.0)
